environmental_insights/__init__.py
environmental_insights/air_pollution_functions.py
environmental_insights/data.py
environmental_insights/download.py
environmental_insights/environmental_insights_data/supporting_data/.gitkeep
environmental_insights/environmental_insights_data/supporting_data/025latlong_world_grids.gpkg
environmental_insights/environmental_insights_data/supporting_data/1km_uk_grids.gpkg
environmental_insights/environmental_insights_data/supporting_data/1km_uk_grids_outline.gpkg
environmental_insights/models.py
environmental_insights/variables.py
environmental_insights-0.3.0.dist-info/LICENSE
environmental_insights-0.3.0.dist-info/METADATA
environmental_insights-0.3.0.dist-info/WHEEL
environmental_insights-0.3.0.dist-info/RECORD
