Metadata-Version: 2.3
Name: environmental_insights
Version: 0.3.0
Summary: A Python package for democratizing access to ambient air pollution data and predictive analytics.
License: GPL-3.0-or-later
Keywords: air pollution,predictive analytics,environmental data,geospatial analysis
Author: Liam J. Berrisford
Author-email: l.berrisford3@exeter.ac.uk
Requires-Python: >=3.10,<4.0
Classifier: License :: OSI Approved :: GNU General Public License v3 or later (GPLv3+)
Classifier: Programming Language :: Python :: 3
Classifier: Programming Language :: Python :: 3.10
Classifier: Programming Language :: Python :: 3.11
Classifier: Programming Language :: Python :: 3.12
Classifier: Programming Language :: Python :: 3.13
Requires-Dist: beautifulsoup4 (>=4.13.4,<5.0.0)
Requires-Dist: geopandas (>=1.0.1,<2.0.0)
Requires-Dist: lightgbm
Requires-Dist: matplotlib
Requires-Dist: netcdf4 (>=1.7.2,<2.0.0)
Requires-Dist: overpy
Requires-Dist: pandas
Requires-Dist: pyarrow
Requires-Dist: pyogrio
Requires-Dist: requests
Requires-Dist: scikit-learn (>=1.6.1,<2.0.0)
Requires-Dist: scipy
Requires-Dist: shapely
Requires-Dist: xarray (>=2025.4.0,<2026.0.0)
